giteasy/__init__.py
giteasy/github_repo.py
giteasy/githubb.py
giteasy-10.2.2.dist-info/METADATA
giteasy-10.2.2.dist-info/WHEEL
giteasy-10.2.2.dist-info/licenses/LICENSE
giteasy-10.2.2.dist-info/RECORD
