Metadata-Version: 2.1
Name: giteasy
Version: 10.2.2
Summary: A simple tool to get last/full version of a github repository and committing back to it
Project-URL: Homepage, https://github.com/imahdimir/giteasy
Project-URL: Bug Tracker, https://github.com/imahdimir/giteasy/issues
Author-email: Mahdi Mir <imahdimir@gmail.com>
License: MIT License
License-File: LICENSE
Classifier: Intended Audience :: Developers
Classifier: License :: OSI Approved :: MIT License
Classifier: Operating System :: OS Independent
Classifier: Programming Language :: Python
Classifier: Programming Language :: Python :: Implementation :: PyPy
Classifier: Topic :: Utilities
Requires-Dist: dulwich
Requires-Dist: mirutil
Requires-Dist: mtok
Requires-Dist: purl~=1.6
Requires-Dist: pygithub
